{
    "prestations": [
        {
            "type": "car",
            "price": {
                "currency": "GBP",
                "supplier_value": 117.54,
                "value": 117.54,
                "fee": 0
            },
            "details": {
                "offer_id": "9c98ab1ac5ce055f57dfc435bfd9a87743f19f40fcb27499b1acbcf62a827667",
                "contract_id": "53838971",
                "rental_days_nb": 2,
                "days": 2,
                "km_offer": {
                    "included": 250,
                    "price_per_unit": {
                        "value": 0.37,
                        "currency": "GBP"
                    },
                    "wanted": 0,
                    "unit": "km"
                },
                "car": {
                    "categorie": {
                        "code": "MBMR",
                        "libelle": "Mini"
                    },
                    "pictures": [
                        "https://static.europcar.com/carvisuals/partners/835x557/MBMR_FR.png"
                    ],
                    "sample": "RENAULT TWINGO",
                    "doors": 3,
                    "seats": 4,
                    "is_auto": false,
                    "has_AC": true,
                    "co2": {
                        "value": 98,
                        "unit": "g/km"
                    },
                    "fuel": {
                        "value": "UL",
                        "libelle": "petrol"
                    },
                    "power": {
                        "kilo_watt": 55,
                        "horse_power": 75
                    },
                    "sizing": {
                        "width": 1.65,
                        "weight": null,
                        "length": 3.6,
                        "height": 1.47,
                        "unit": "m"
                    },
                    "insurances": [
                        {
                            "quantity": "1",
                            "code": "ECOLOGIC",
                            "type": "mandatory",
                            "label": "Environmental contribution",
                            "unit_price": {
                                "value": 1.05,
                                "currency": "GBP"
                            }
                        }
                    ],
                    "ancillaries": [],
                    "baggage_quantity": 1
                },
                "scheduler": {
                    "origin": [
                        {
                            "begin": "2020-01-20T08:00:00Z",
                            "end": "2020-01-20T13:00:00Z",
                            "type": "General"
                        },
                        {
                            "begin": "2020-01-20T14:00:00Z",
                            "end": "2020-01-20T18:00:00Z",
                            "type": "General"
                        }
                    ],
                    "destination": [
                        {
                            "begin": "2020-01-21T08:00:00Z",
                            "end": "2020-01-21T13:00:00Z",
                            "type": "General"
                        },
                        {
                            "begin": "2020-01-21T14:00:00Z",
                            "end": "2020-01-21T18:00:00Z",
                            "type": "General"
                        }
                    ]
                },
                "itinerary": {
                    "origin": {
                        "datetime": "2020-01-20T08:00:00Z",
                        "location": {
                            "code": "PARE08",
                            "name": "BONDY *UTILITAIRES*",
                            "address": {
                                "street_name": "95 AVENUE GALLIENI",
                                "city": "BONDY",
                                "postal_code": "93140",
                                "country": "France",
                                "country_code": "FR"
                            },
                            "coordinates": {
                                "latitude": 48.9065,
                                "longitude": 2.4805
                            }
                        }
                    },
                    "destination": {
                        "datetime": "2020-01-21T18:00:00Z",
                        "location": {
                            "code": "PARE08",
                            "name": "BONDY *UTILITAIRES*",
                            "address": {
                                "street_name": "95 AVENUE GALLIENI",
                                "city": "BONDY",
                                "postal_code": "93140",
                                "country": "France",
                                "country_code": "FR"
                            },
                            "coordinates": {
                                "latitude": 48.9065,
                                "longitude": 2.4805
                            }
                        }
                    },
                    "carrier": {
                        "code": "europcar",
                        "name": "Europcar"
                    }
                },
                "delivery": {
                    "origin": {
                        "location": {
                            "name": "[TP] Cedric & TEST",
                            "address": {
                                "street_name": "Rue super méga longue avec des %, ^^, '\\\"'é('\\\"(àç_éà'&à384%µ^*",
                                "postal_code": "12345",
                                "city": "paris",
                                "country": "France",
                                "country_code": "FR"
                            },
                            "coordinates": {
                                "latitude": 48.8351051,
                                "longitude": 2.403595
                            }
                        },
                        "id": null,
                        "type": "customer",
                        "datetime": "2020-01-20T08:00:00Z"
                    },
                    "destination": {
                        "location": {
                            "name": "[TP] Cedric & TEST",
                            "address": {
                                "street_name": "Rue super méga longue avec des %, ^^, '\\\"'é('\\\"(àç_éà'&à384%µ^*",
                                "postal_code": "12345",
                                "city": "paris",
                                "country": "France",
                                "country_code": "FR"
                            },
                            "coordinates": {
                                "latitude": 48.8351051,
                                "longitude": 2.403595
                            }
                        },
                        "id": null,
                        "type": "customer",
                        "datetime": "2020-01-21T18:00:00Z"
                    }
                },
                "category": "Mini",
                "model": "RENAULT TWINGO",
                "is_auto": false,
                "has_AC": true,
                "fuel_type": "petrol",
                "tarif_type": "none",
                "km_price": 0.37,
                "driver": {
                    "min_category_age": 18,
                    "min_country_age": 18,
                    "min_young_age": 26,
                    "min_licence_period": "0 months"
                },
                "luggage_nb": 1
            },
            "supplier": "europcar"
        }
    ],
    "total_price": {
        "currency": "GBP",
        "supplier_value": 117.54,
        "value": 117.54,
        "fee": 4,
        "markup": 0
    },
    "traveller": {
        "uid": "momoxxxmoh",
        "last_name": "Momo",
        "first_name": "Mohamed",
        "birthdate": "1998-01-15",
        "email": "mohamed@travelplanet.fr",
        "phone": "+33972100590"
    },
    "travellers": [
        {
            "uid": "momoxxxmoh",
            "last_name": "Momo",
            "first_name": "Mohamed",
            "birthdate": "1998-01-15",
            "email": "mohamed@travelplanet.fr",
            "phone": "+33972100590"
        }
    ],
    "site_id": "Q46X",
    "status": {
        "code": "CONFIRMED",
        "name": "Validée"
    },
    "insertion_date": "2020-01-14T12:38:53.372Z",
    "end_date": "2020-01-20T08:00:00.000Z",
    "creation_date": "2020-01-14T12:38:03.367Z",
    "session_id": "0b592140-3622-11ea-8c81-b5740d0b19ab",
    "arranger": {
        "uid": "momoxxxmoh",
        "first_name": "Mohamed",
        "last_name": "Momo"
    },
    "is_demo": true,
    "departure_date": "2020-01-20T08:00:00Z",
    "trip": {
        "departure_date": "2020-01-20",
        "return_date": "2020-01-21",
        "origin": {
            "country_code": "FR"
        },
        "destination": {
            "country_code": "FR"
        }
    },
    "fees": [
        {
            "id": "application_fee",
            "price": {
                "currency": "EUR",
                "fee": 4
            },
            "type": "car",
            "transaction_code": "online",
            "details": {
                "taxes": {
                    "vat": {
                        "is_included": false,
                        "country_code": "FR"
                    }
                },
                "is_international": true
            }
        }
    ],
    "prestations_uuid": "945e1970-36ca-11ea-afe8-81b13653e0c9",
    "prestations_options": {
        "cars": [
            {
                "driver": {
                    "uid": "momoxxxmoh",
                    "last_name": "Momo",
                    "first_name": "Mohamed",
                    "birthdate": "1998-01-15",
                    "title": "MR",
                    "licence": [],
                    "email": "mohamed@travelplanet.fr",
                    "phone": "+33972100590"
                },
                "origin_delivery": {
                    "dateTime": "2020-01-20T08:00:00Z",
                    "address": {
                        "street_name": "Rue super méga longue avec des %, ^^, '\\\"'é('\\\"(àç_éà'&à384%µ^*",
                        "postal_code": "12345",
                        "city": "paris",
                        "country": "France",
                        "country_code": "FR"
                    }
                },
                "destination_delivery": {
                    "dateTime": "2020-01-21T18:00:00Z",
                    "address": {
                        "street_name": "Rue super méga longue avec des %, ^^, '\\\"'é('\\\"(àç_éà'&à384%µ^*",
                        "postal_code": "12345",
                        "city": "paris",
                        "country": "France",
                        "country_code": "FR"
                    }
                },
                "insurances": [
                    {
                        "key": "ECOLOGIC",
                        "value": 1
                    }
                ],
                "ancillaries": []
            }
        ]
    },
    "uuid": "b4ff37e0-36ca-11ea-b196-bf3e7bf72d40",
    "parent_uuid": "b4d93950-36ca-11ea-b196-bf3e7bf72d40",
    "tp_id": "ACGXF",
    "supplier": "europcar",
    "type": "car",
    "actions": {
        "creation": {
            "timestamp": "2020-01-14T12:38:03.367Z",
            "user_id": "momoxxxmoh",
            "first_name": "Mohamed",
            "last_name": "Momo"
        },
        "request_approval": {
            "timestamp": "2020-01-14T12:38:38.801Z",
            "user_id": "momoxxxmoh",
            "first_name": "Mohamed",
            "last_name": "Momo"
        }
    },
    "approver": {
        "uid": "momoxxxmoh",
        "civility": "MR",
        "first_name": "Mohamed",
        "last_name": "Momo",
        "phone": "972100590"
    },
    "supplier_id": "1113209603",
    "additional_infos": {
        "voucher": {
            "voucher_id": "57859319"
        }
    }
}